<?xml version="1.0" encoding="utf-8" ?>
<areapionts>
    	    <areapiont>
			<year>2012</year>
			<specialname>汉语言文学</specialname>
			<maxfs>542</maxfs>
			<varfs>534</varfs>
			<pc>二批</pc>
			<stype>文科</stype>
		</areapiont>
	    <areapiont>
			<year>2011</year>
			<specialname>工商管理</specialname>
			<maxfs>500</maxfs>
			<varfs>494</varfs>
			<pc>二批</pc>
			<stype>文科</stype>
		</areapiont>
	    <areapiont>
			<year>2010</year>
			<specialname>工商管理</specialname>
			<maxfs>473</maxfs>
			<varfs>470</varfs>
			<pc>二批</pc>
			<stype>文科</stype>
		</areapiont>
	    <areapiont>
			<year>2009</year>
			<specialname>汉语言文学</specialname>
			<maxfs>497</maxfs>
			<varfs>497</varfs>
			<pc>二批</pc>
			<stype>文科</stype>
		</areapiont>
	    <areapiont>
			<year>2009</year>
			<specialname>信息管理与信息系统</specialname>
			<maxfs>509</maxfs>
			<varfs>509</varfs>
			<pc>二批</pc>
			<stype>文科</stype>
		</areapiont>
	    <areapiont>
			<year>2008</year>
			<specialname>国际经济与贸易</specialname>
			<maxfs>478</maxfs>
			<varfs>478</varfs>
			<pc>二批</pc>
			<stype>文科</stype>
		</areapiont>
	    <areapiont>
			<year>2008</year>
			<specialname>信息管理与信息系统</specialname>
			<maxfs>488</maxfs>
			<varfs>488</varfs>
			<pc>二批</pc>
			<stype>文科</stype>
		</areapiont>
</areapionts>