<?xml version="1.0" encoding="utf-8" ?>
<areapionts>
    	    <areapiont>
			<year>2014</year>
			<specialname>通信工程(指挥类)</specialname>
			<maxfs>539</maxfs>
			<varfs>--</varfs>
			<pc>提前</pc>
			<stype>理科</stype>
		</areapiont>
	    <areapiont>
			<year>2014</year>
			<specialname>交通运输(指挥类)</specialname>
			<maxfs>564</maxfs>
			<varfs>--</varfs>
			<pc>提前</pc>
			<stype>理科</stype>
		</areapiont>
	    <areapiont>
			<year>2014</year>
			<specialname>地理科学类(含地理科学、自然地理与资源环境、人文地理与城乡规划)</specialname>
			<maxfs>485</maxfs>
			<varfs>--</varfs>
			<pc>二批</pc>
			<stype>理科</stype>
		</areapiont>
	    <areapiont>
			<year>2014</year>
			<specialname>数学类(含数学与应用数学、信息与计算科学)</specialname>
			<maxfs>508</maxfs>
			<varfs>--</varfs>
			<pc>二批</pc>
			<stype>理科</stype>
		</areapiont>
	    <areapiont>
			<year>2014</year>
			<specialname>机械类(含机械设计制造及其自动化、车辆工程、机械电子工程)</specialname>
			<maxfs>511</maxfs>
			<varfs>--</varfs>
			<pc>二批</pc>
			<stype>理科</stype>
		</areapiont>
	    <areapiont>
			<year>2014</year>
			<specialname>植物保护</specialname>
			<maxfs>518</maxfs>
			<varfs>--</varfs>
			<pc>二批</pc>
			<stype>理科</stype>
		</areapiont>
	    <areapiont>
			<year>2014</year>
			<specialname>信息管理与信息系统</specialname>
			<maxfs>501</maxfs>
			<varfs>--</varfs>
			<pc>二批</pc>
			<stype>理科</stype>
		</areapiont>
	    <areapiont>
			<year>2014</year>
			<specialname>地理科学类</specialname>
			<maxfs>--</maxfs>
			<varfs>485</varfs>
			<pc>二批</pc>
			<stype>理科</stype>
		</areapiont>
	    <areapiont>
			<year>2014</year>
			<specialname>数学类</specialname>
			<maxfs>--</maxfs>
			<varfs>498</varfs>
			<pc>二批</pc>
			<stype>理科</stype>
		</areapiont>
	    <areapiont>
			<year>2014</year>
			<specialname>机械类</specialname>
			<maxfs>--</maxfs>
			<varfs>510</varfs>
			<pc>二批</pc>
			<stype>理科</stype>
		</areapiont>
	    <areapiont>
			<year>2013</year>
			<specialname>信息管理与信息系统</specialname>
			<maxfs>474</maxfs>
			<varfs>469</varfs>
			<pc>二批</pc>
			<stype>理科</stype>
		</areapiont>
	    <areapiont>
			<year>2013</year>
			<specialname>机械类</specialname>
			<maxfs>501</maxfs>
			<varfs>496</varfs>
			<pc>二批</pc>
			<stype>理科</stype>
		</areapiont>
	    <areapiont>
			<year>2013</year>
			<specialname>地理科学</specialname>
			<maxfs>480</maxfs>
			<varfs>470</varfs>
			<pc>二批</pc>
			<stype>理科</stype>
		</areapiont>
	    <areapiont>
			<year>2013</year>
			<specialname>数学类</specialname>
			<maxfs>480</maxfs>
			<varfs>478</varfs>
			<pc>二批</pc>
			<stype>理科</stype>
		</areapiont>
	    <areapiont>
			<year>2012</year>
			<specialname>园林</specialname>
			<maxfs>483</maxfs>
			<varfs>475</varfs>
			<pc>二批</pc>
			<stype>理科</stype>
		</areapiont>
	    <areapiont>
			<year>2012</year>
			<specialname>电子商务</specialname>
			<maxfs>499</maxfs>
			<varfs>488</varfs>
			<pc>二批</pc>
			<stype>理科</stype>
		</areapiont>
	    <areapiont>
			<year>2012</year>
			<specialname>数学</specialname>
			<maxfs>456</maxfs>
			<varfs>446</varfs>
			<pc>二批</pc>
			<stype>理科</stype>
		</areapiont>
	    <areapiont>
			<year>2011</year>
			<specialname>经济学</specialname>
			<maxfs>526</maxfs>
			<varfs>519</varfs>
			<pc>二批</pc>
			<stype>理科</stype>
		</areapiont>
	    <areapiont>
			<year>2011</year>
			<specialname>数学与应用数学</specialname>
			<maxfs>518</maxfs>
			<varfs>516</varfs>
			<pc>二批</pc>
			<stype>理科</stype>
		</areapiont>
	    <areapiont>
			<year>2011</year>
			<specialname>地理科学</specialname>
			<maxfs>489</maxfs>
			<varfs>485</varfs>
			<pc>二批</pc>
			<stype>理科</stype>
		</areapiont>
	    <areapiont>
			<year>2011</year>
			<specialname>种子科学与工程</specialname>
			<maxfs>485</maxfs>
			<varfs>483</varfs>
			<pc>二批</pc>
			<stype>理科</stype>
		</areapiont>
	    <areapiont>
			<year>2011</year>
			<specialname>植物保护</specialname>
			<maxfs>501</maxfs>
			<varfs>497</varfs>
			<pc>二批</pc>
			<stype>理科</stype>
		</areapiont>
	    <areapiont>
			<year>2011</year>
			<specialname>计算机科学与技术</specialname>
			<maxfs>501</maxfs>
			<varfs>498</varfs>
			<pc>二批</pc>
			<stype>理科</stype>
		</areapiont>
	    <areapiont>
			<year>2011</year>
			<specialname>建筑学</specialname>
			<maxfs>505</maxfs>
			<varfs>502</varfs>
			<pc>二批</pc>
			<stype>理科</stype>
		</areapiont>
	    <areapiont>
			<year>2010</year>
			<specialname>数学与应用数学</specialname>
			<maxfs>461</maxfs>
			<varfs>458</varfs>
			<pc>二批</pc>
			<stype>理科</stype>
		</areapiont>
	    <areapiont>
			<year>2010</year>
			<specialname>地理科学</specialname>
			<maxfs>469</maxfs>
			<varfs>459</varfs>
			<pc>二批</pc>
			<stype>理科</stype>
		</areapiont>
	    <areapiont>
			<year>2010</year>
			<specialname>计算机科学与技术</specialname>
			<maxfs>466</maxfs>
			<varfs>459</varfs>
			<pc>二批</pc>
			<stype>理科</stype>
		</areapiont>
	    <areapiont>
			<year>2010</year>
			<specialname>种子科学与工程</specialname>
			<maxfs>469</maxfs>
			<varfs>460</varfs>
			<pc>二批</pc>
			<stype>理科</stype>
		</areapiont>
	    <areapiont>
			<year>2010</year>
			<specialname>经济学</specialname>
			<maxfs>492</maxfs>
			<varfs>474</varfs>
			<pc>二批</pc>
			<stype>理科</stype>
		</areapiont>
	    <areapiont>
			<year>2010</year>
			<specialname>建筑学</specialname>
			<maxfs>526</maxfs>
			<varfs>497</varfs>
			<pc>二批</pc>
			<stype>理科</stype>
		</areapiont>
	    <areapiont>
			<year>2009</year>
			<specialname>经济学</specialname>
			<maxfs>504</maxfs>
			<varfs>477</varfs>
			<pc>二批</pc>
			<stype>理科</stype>
		</areapiont>
	    <areapiont>
			<year>2009</year>
			<specialname>地理科学</specialname>
			<maxfs>481</maxfs>
			<varfs>477</varfs>
			<pc>二批</pc>
			<stype>理科</stype>
		</areapiont>
	    <areapiont>
			<year>2009</year>
			<specialname>数学与应用数学</specialname>
			<maxfs>491</maxfs>
			<varfs>482</varfs>
			<pc>二批</pc>
			<stype>理科</stype>
		</areapiont>
	    <areapiont>
			<year>2009</year>
			<specialname>建筑学</specialname>
			<maxfs>513</maxfs>
			<varfs>486</varfs>
			<pc>二批</pc>
			<stype>理科</stype>
		</areapiont>
	    <areapiont>
			<year>2008</year>
			<specialname>化学</specialname>
			<maxfs>565</maxfs>
			<varfs>553</varfs>
			<pc>二批</pc>
			<stype>理科</stype>
		</areapiont>
	    <areapiont>
			<year>2008</year>
			<specialname>生物工程</specialname>
			<maxfs>583</maxfs>
			<varfs>550</varfs>
			<pc>二批</pc>
			<stype>理科</stype>
		</areapiont>
	    <areapiont>
			<year>2008</year>
			<specialname>化学工程与工艺</specialname>
			<maxfs>551</maxfs>
			<varfs>548</varfs>
			<pc>二批</pc>
			<stype>理科</stype>
		</areapiont>
	    <areapiont>
			<year>2008</year>
			<specialname>通信工程</specialname>
			<maxfs>575</maxfs>
			<varfs>566</varfs>
			<pc>二批</pc>
			<stype>理科</stype>
		</areapiont>
	    <areapiont>
			<year>2008</year>
			<specialname>信息与计算科学</specialname>
			<maxfs>553</maxfs>
			<varfs>543</varfs>
			<pc>二批</pc>
			<stype>理科</stype>
		</areapiont>
	    <areapiont>
			<year>2008</year>
			<specialname>材料化学</specialname>
			<maxfs>549</maxfs>
			<varfs>542</varfs>
			<pc>二批</pc>
			<stype>理科</stype>
		</areapiont>
	    <areapiont>
			<year>2007</year>
			<specialname>生物科学</specialname>
			<maxfs>594</maxfs>
			<varfs>556</varfs>
			<pc>二批</pc>
			<stype>理科</stype>
		</areapiont>
	    <areapiont>
			<year>2007</year>
			<specialname>通信工程</specialname>
			<maxfs>587</maxfs>
			<varfs>562</varfs>
			<pc>二批</pc>
			<stype>理科</stype>
		</areapiont>
	    <areapiont>
			<year>2007</year>
			<specialname>化学</specialname>
			<maxfs>578</maxfs>
			<varfs>556</varfs>
			<pc>二批</pc>
			<stype>理科</stype>
		</areapiont>
	    <areapiont>
			<year>2007</year>
			<specialname>材料化学</specialname>
			<maxfs>576</maxfs>
			<varfs>541</varfs>
			<pc>二批</pc>
			<stype>理科</stype>
		</areapiont>
	    <areapiont>
			<year>2006</year>
			<specialname>数学与应用数学</specialname>
			<maxfs>569</maxfs>
			<varfs>550</varfs>
			<pc>二批</pc>
			<stype>理科</stype>
		</areapiont>
	    <areapiont>
			<year>2006</year>
			<specialname>物理学</specialname>
			<maxfs>559</maxfs>
			<varfs>552</varfs>
			<pc>二批</pc>
			<stype>理科</stype>
		</areapiont>
	    <areapiont>
			<year>2006</year>
			<specialname>化学</specialname>
			<maxfs>568</maxfs>
			<varfs>550</varfs>
			<pc>二批</pc>
			<stype>理科</stype>
		</areapiont>
	    <areapiont>
			<year>2006</year>
			<specialname>生物科学</specialname>
			<maxfs>573</maxfs>
			<varfs>538</varfs>
			<pc>二批</pc>
			<stype>理科</stype>
		</areapiont>
	    <areapiont>
			<year>2006</year>
			<specialname>经济学</specialname>
			<maxfs>571</maxfs>
			<varfs>553</varfs>
			<pc>二批</pc>
			<stype>理科</stype>
		</areapiont>
	    <areapiont>
			<year>2005</year>
			<specialname>数学与应用数学</specialname>
			<maxfs>560</maxfs>
			<varfs>556</varfs>
			<pc>二批</pc>
			<stype>理科</stype>
		</areapiont>
	    <areapiont>
			<year>2005</year>
			<specialname>物理学</specialname>
			<maxfs>595</maxfs>
			<varfs>565</varfs>
			<pc>二批</pc>
			<stype>理科</stype>
		</areapiont>
	    <areapiont>
			<year>2005</year>
			<specialname>生物科学</specialname>
			<maxfs>576</maxfs>
			<varfs>543</varfs>
			<pc>二批</pc>
			<stype>理科</stype>
		</areapiont>
	    <areapiont>
			<year>2005</year>
			<specialname>信息与计算科学</specialname>
			<maxfs>598</maxfs>
			<varfs>572</varfs>
			<pc>二批</pc>
			<stype>理科</stype>
		</areapiont>
	    <areapiont>
			<year>2005</year>
			<specialname>计算机科学与技术</specialname>
			<maxfs>577</maxfs>
			<varfs>563</varfs>
			<pc>二批</pc>
			<stype>理科</stype>
		</areapiont>
</areapionts>