<?xml version="1.0" encoding="utf-8" ?>
<areapionts>
    	    <areapiont>
			<year>2015</year>
			<specialname>文化产业管理</specialname>
			<maxfs>530</maxfs>
			<varfs>530</varfs>
			<pc>二批</pc>
			<stype>文科</stype>
		</areapiont>
	    <areapiont>
			<year>2014</year>
			<specialname>文化产业管理</specialname>
			<maxfs>--</maxfs>
			<varfs>513</varfs>
			<pc>二批</pc>
			<stype>文科</stype>
		</areapiont>
	    <areapiont>
			<year>2009</year>
			<specialname>法学</specialname>
			<maxfs>494</maxfs>
			<varfs>494</varfs>
			<pc>二批</pc>
			<stype>文科</stype>
		</areapiont>
	    <areapiont>
			<year>2008</year>
			<specialname>法学</specialname>
			<maxfs>479</maxfs>
			<varfs>479</varfs>
			<pc>二批</pc>
			<stype>文科</stype>
		</areapiont>
	    <areapiont>
			<year>2007</year>
			<specialname>法学</specialname>
			<maxfs>506</maxfs>
			<varfs>506</varfs>
			<pc>二批</pc>
			<stype>文科</stype>
		</areapiont>
	    <areapiont>
			<year>2007</year>
			<specialname>旅游管理</specialname>
			<maxfs>500</maxfs>
			<varfs>500</varfs>
			<pc>二批</pc>
			<stype>文科</stype>
		</areapiont>
	    <areapiont>
			<year>2006</year>
			<specialname>法学</specialname>
			<maxfs>509</maxfs>
			<varfs>509</varfs>
			<pc>二批</pc>
			<stype>文科</stype>
		</areapiont>
	    <areapiont>
			<year>2006</year>
			<specialname>旅游管理</specialname>
			<maxfs>494</maxfs>
			<varfs>494</varfs>
			<pc>二批</pc>
			<stype>文科</stype>
		</areapiont>
</areapionts>