<?xml version="1.0" encoding="utf-8" ?>
<areapionts>
    	    <areapiont>
			<year>2015</year>
			<specialname>土木工程</specialname>
			<maxfs>462</maxfs>
			<varfs>452</varfs>
			<pc>二批</pc>
			<stype>理科</stype>
		</areapiont>
	    <areapiont>
			<year>2015</year>
			<specialname>英语</specialname>
			<maxfs>467</maxfs>
			<varfs>457</varfs>
			<pc>二批</pc>
			<stype>理科</stype>
		</areapiont>
	    <areapiont>
			<year>2014</year>
			<specialname>土木工程</specialname>
			<maxfs>--</maxfs>
			<varfs>473</varfs>
			<pc>二批</pc>
			<stype>理科</stype>
		</areapiont>
	    <areapiont>
			<year>2014</year>
			<specialname>英语</specialname>
			<maxfs>--</maxfs>
			<varfs>474</varfs>
			<pc>二批</pc>
			<stype>理科</stype>
		</areapiont>
	    <areapiont>
			<year>2014</year>
			<specialname>网络工程</specialname>
			<maxfs>--</maxfs>
			<varfs>475</varfs>
			<pc>二批</pc>
			<stype>理科</stype>
		</areapiont>
	    <areapiont>
			<year>2014</year>
			<specialname>通信工程</specialname>
			<maxfs>--</maxfs>
			<varfs>476</varfs>
			<pc>二批</pc>
			<stype>理科</stype>
		</areapiont>
	    <areapiont>
			<year>2014</year>
			<specialname>应用心理学</specialname>
			<maxfs>--</maxfs>
			<varfs>479</varfs>
			<pc>二批</pc>
			<stype>理科</stype>
		</areapiont>
	    <areapiont>
			<year>2013</year>
			<specialname>经济统计学</specialname>
			<maxfs>467</maxfs>
			<varfs>465</varfs>
			<pc>二批</pc>
			<stype>理科</stype>
		</areapiont>
	    <areapiont>
			<year>2013</year>
			<specialname>财政学</specialname>
			<maxfs>473</maxfs>
			<varfs>465</varfs>
			<pc>二批</pc>
			<stype>理科</stype>
		</areapiont>
	    <areapiont>
			<year>2013</year>
			<specialname>教育技术学</specialname>
			<maxfs>483</maxfs>
			<varfs>470</varfs>
			<pc>二批</pc>
			<stype>理科</stype>
		</areapiont>
	    <areapiont>
			<year>2013</year>
			<specialname>临床医学</specialname>
			<maxfs>473</maxfs>
			<varfs>467</varfs>
			<pc>二批</pc>
			<stype>理科</stype>
		</areapiont>
	    <areapiont>
			<year>2013</year>
			<specialname>电子信息科学与技术</specialname>
			<maxfs>474</maxfs>
			<varfs>468</varfs>
			<pc>二批</pc>
			<stype>理科</stype>
		</areapiont>
	    <areapiont>
			<year>2011</year>
			<specialname>统计学</specialname>
			<maxfs>542</maxfs>
			<varfs>536</varfs>
			<pc>二批</pc>
			<stype>理科</stype>
		</areapiont>
	    <areapiont>
			<year>2011</year>
			<specialname>电子信息科学与技术</specialname>
			<maxfs>535</maxfs>
			<varfs>528</varfs>
			<pc>二批</pc>
			<stype>理科</stype>
		</areapiont>
	    <areapiont>
			<year>2011</year>
			<specialname>通信工程</specialname>
			<maxfs>566</maxfs>
			<varfs>537</varfs>
			<pc>二批</pc>
			<stype>理科</stype>
		</areapiont>
	    <areapiont>
			<year>2011</year>
			<specialname>计算机科学与技术</specialname>
			<maxfs>552</maxfs>
			<varfs>536</varfs>
			<pc>二批</pc>
			<stype>理科</stype>
		</areapiont>
	    <areapiont>
			<year>2011</year>
			<specialname>财政学</specialname>
			<maxfs>551</maxfs>
			<varfs>540</varfs>
			<pc>二批</pc>
			<stype>理科</stype>
		</areapiont>
	    <areapiont>
			<year>2011</year>
			<specialname>金融学</specialname>
			<maxfs>560</maxfs>
			<varfs>539</varfs>
			<pc>二批</pc>
			<stype>理科</stype>
		</areapiont>
	    <areapiont>
			<year>2011</year>
			<specialname>临床医学</specialname>
			<maxfs>543</maxfs>
			<varfs>536</varfs>
			<pc>二批</pc>
			<stype>理科</stype>
		</areapiont>
	    <areapiont>
			<year>2010</year>
			<specialname>通信工程</specialname>
			<maxfs>514</maxfs>
			<varfs>509</varfs>
			<pc>二批</pc>
			<stype>理科</stype>
		</areapiont>
	    <areapiont>
			<year>2010</year>
			<specialname>计算机科学与技术</specialname>
			<maxfs>515</maxfs>
			<varfs>509</varfs>
			<pc>二批</pc>
			<stype>理科</stype>
		</areapiont>
	    <areapiont>
			<year>2010</year>
			<specialname>金融学</specialname>
			<maxfs>521</maxfs>
			<varfs>510</varfs>
			<pc>二批</pc>
			<stype>理科</stype>
		</areapiont>
	    <areapiont>
			<year>2010</year>
			<specialname>会计学</specialname>
			<maxfs>516</maxfs>
			<varfs>511</varfs>
			<pc>二批</pc>
			<stype>理科</stype>
		</areapiont>
	    <areapiont>
			<year>2010</year>
			<specialname>电子信息科学与技术</specialname>
			<maxfs>519</maxfs>
			<varfs>513</varfs>
			<pc>二批</pc>
			<stype>理科</stype>
		</areapiont>
	    <areapiont>
			<year>2010</year>
			<specialname>英语</specialname>
			<maxfs>551</maxfs>
			<varfs>522</varfs>
			<pc>二批</pc>
			<stype>理科</stype>
		</areapiont>
	    <areapiont>
			<year>2010</year>
			<specialname>临床医学</specialname>
			<maxfs>540</maxfs>
			<varfs>522</varfs>
			<pc>二批</pc>
			<stype>理科</stype>
		</areapiont>
	    <areapiont>
			<year>2009</year>
			<specialname>电子信息科学与技术</specialname>
			<maxfs>497</maxfs>
			<varfs>495</varfs>
			<pc>二批</pc>
			<stype>理科</stype>
		</areapiont>
	    <areapiont>
			<year>2009</year>
			<specialname>通信工程</specialname>
			<maxfs>505</maxfs>
			<varfs>498</varfs>
			<pc>二批</pc>
			<stype>理科</stype>
		</areapiont>
	    <areapiont>
			<year>2009</year>
			<specialname>工商管理</specialname>
			<maxfs>500</maxfs>
			<varfs>498</varfs>
			<pc>二批</pc>
			<stype>理科</stype>
		</areapiont>
	    <areapiont>
			<year>2009</year>
			<specialname>英语</specialname>
			<maxfs>506</maxfs>
			<varfs>499</varfs>
			<pc>二批</pc>
			<stype>理科</stype>
		</areapiont>
	    <areapiont>
			<year>2009</year>
			<specialname>临床医学</specialname>
			<maxfs>509</maxfs>
			<varfs>499</varfs>
			<pc>二批</pc>
			<stype>理科</stype>
		</areapiont>
	    <areapiont>
			<year>2009</year>
			<specialname>计算机科学与技术</specialname>
			<maxfs>512</maxfs>
			<varfs>500</varfs>
			<pc>二批</pc>
			<stype>理科</stype>
		</areapiont>
	    <areapiont>
			<year>2009</year>
			<specialname>教育技术学</specialname>
			<maxfs>531</maxfs>
			<varfs>505</varfs>
			<pc>二批</pc>
			<stype>理科</stype>
		</areapiont>
	    <areapiont>
			<year>2008</year>
			<specialname>护理学</specialname>
			<maxfs>507</maxfs>
			<varfs>504</varfs>
			<pc>二批</pc>
			<stype>理科</stype>
		</areapiont>
	    <areapiont>
			<year>2008</year>
			<specialname>临床医学</specialname>
			<maxfs>511</maxfs>
			<varfs>507</varfs>
			<pc>二批</pc>
			<stype>理科</stype>
		</areapiont>
	    <areapiont>
			<year>2008</year>
			<specialname>教育技术学</specialname>
			<maxfs>511</maxfs>
			<varfs>506</varfs>
			<pc>二批</pc>
			<stype>理科</stype>
		</areapiont>
	    <areapiont>
			<year>2008</year>
			<specialname>英语</specialname>
			<maxfs>509</maxfs>
			<varfs>506</varfs>
			<pc>二批</pc>
			<stype>理科</stype>
		</areapiont>
	    <areapiont>
			<year>2008</year>
			<specialname>电子信息科学与技术</specialname>
			<maxfs>513</maxfs>
			<varfs>507</varfs>
			<pc>二批</pc>
			<stype>理科</stype>
		</areapiont>
	    <areapiont>
			<year>2008</year>
			<specialname>工商管理</specialname>
			<maxfs>509</maxfs>
			<varfs>507</varfs>
			<pc>二批</pc>
			<stype>理科</stype>
		</areapiont>
	    <areapiont>
			<year>2008</year>
			<specialname>通信工程</specialname>
			<maxfs>513</maxfs>
			<varfs>508</varfs>
			<pc>二批</pc>
			<stype>理科</stype>
		</areapiont>
	    <areapiont>
			<year>2007</year>
			<specialname>教育技术学</specialname>
			<maxfs>507</maxfs>
			<varfs>505</varfs>
			<pc>二批</pc>
			<stype>理科</stype>
		</areapiont>
	    <areapiont>
			<year>2007</year>
			<specialname>国际经济与贸易</specialname>
			<maxfs>527</maxfs>
			<varfs>512</varfs>
			<pc>二批</pc>
			<stype>理科</stype>
		</areapiont>
	    <areapiont>
			<year>2007</year>
			<specialname>会计学</specialname>
			<maxfs>509</maxfs>
			<varfs>507</varfs>
			<pc>二批</pc>
			<stype>理科</stype>
		</areapiont>
	    <areapiont>
			<year>2007</year>
			<specialname>通信工程</specialname>
			<maxfs>509</maxfs>
			<varfs>506</varfs>
			<pc>二批</pc>
			<stype>理科</stype>
		</areapiont>
	    <areapiont>
			<year>2007</year>
			<specialname>工商管理</specialname>
			<maxfs>511</maxfs>
			<varfs>508</varfs>
			<pc>二批</pc>
			<stype>理科</stype>
		</areapiont>
	    <areapiont>
			<year>2007</year>
			<specialname>电子信息科学与技术</specialname>
			<maxfs>513</maxfs>
			<varfs>508</varfs>
			<pc>二批</pc>
			<stype>理科</stype>
		</areapiont>
	    <areapiont>
			<year>2006</year>
			<specialname>国际经济与贸易</specialname>
			<maxfs>510</maxfs>
			<varfs>508</varfs>
			<pc>二批</pc>
			<stype>理科</stype>
		</areapiont>
	    <areapiont>
			<year>2006</year>
			<specialname>计算机科学与技术</specialname>
			<maxfs>517</maxfs>
			<varfs>509</varfs>
			<pc>二批</pc>
			<stype>理科</stype>
		</areapiont>
	    <areapiont>
			<year>2006</year>
			<specialname>临床医学</specialname>
			<maxfs>513</maxfs>
			<varfs>508</varfs>
			<pc>二批</pc>
			<stype>理科</stype>
		</areapiont>
	    <areapiont>
			<year>2006</year>
			<specialname>护理学</specialname>
			<maxfs>509</maxfs>
			<varfs>506</varfs>
			<pc>二批</pc>
			<stype>理科</stype>
		</areapiont>
	    <areapiont>
			<year>2006</year>
			<specialname>教育技术学</specialname>
			<maxfs>513</maxfs>
			<varfs>507</varfs>
			<pc>二批</pc>
			<stype>理科</stype>
		</areapiont>
	    <areapiont>
			<year>2005</year>
			<specialname>信息管理与信息系统</specialname>
			<maxfs>520</maxfs>
			<varfs>495</varfs>
			<pc>二批</pc>
			<stype>理科</stype>
		</areapiont>
</areapionts>